MANIFEST.in
setup.py
django_normalized_filefield.egg-info/PKG-INFO
django_normalized_filefield.egg-info/SOURCES.txt
django_normalized_filefield.egg-info/dependency_links.txt
django_normalized_filefield.egg-info/requires.txt
django_normalized_filefield.egg-info/top_level.txt
normalized_filefield/LICENSE.txt
normalized_filefield/__init__.py
normalized_filefield/cache.py
normalized_filefield/form_field.py
normalized_filefield/helpers.py
normalized_filefield/model_field.py
normalized_filefield/tests.py
normalized_filefield/widget.py